mediqbox/gptchat/__init__.py
mediqbox/gptchat/chat.py
mediqbox_gptchat-0.0.4.dist-info/METADATA
mediqbox_gptchat-0.0.4.dist-info/WHEEL
mediqbox_gptchat-0.0.4.dist-info/top_level.txt
mediqbox_gptchat-0.0.4.dist-info/RECORD
