Metadata-Version: 2.1
Name: mediqbox-gptchat
Version: 0.0.4
Summary: A mediqbox component for using ChatGPT service
Requires-Dist: mediqbox-abc >=0.0.4
Requires-Dist: snqueue >=0.7.0
